dataaug/__init__.py
dataaug/_nbdev.py
dataaug/core.py
dataaug-0.0.1.dist-info/LICENSE
dataaug-0.0.1.dist-info/METADATA
dataaug-0.0.1.dist-info/WHEEL
dataaug-0.0.1.dist-info/entry_points.txt
dataaug-0.0.1.dist-info/top_level.txt
dataaug-0.0.1.dist-info/RECORD
